README.rst
setup.py
terraref/__init__.py
terraref/sampletest.py
terraref/laser3d/__init__.py
terraref/laser3d/laser3d.py
terraref_laser3d.egg-info/PKG-INFO
terraref_laser3d.egg-info/SOURCES.txt
terraref_laser3d.egg-info/dependency_links.txt
terraref_laser3d.egg-info/namespace_packages.txt
terraref_laser3d.egg-info/requires.txt
terraref_laser3d.egg-info/top_level.txt