Metadata-Version: 1.1
Name: terraref-laser3d
Version: 1.5.0
Summary: TERRA-REF laser 3D scanner science package
Home-page: https://github.com/terraref/laser3d
Author: UNKNOWN
Author-email: UNKNOWN
License: UNKNOWN
Keywords: field crop,phenomics,computer vision,remote sensing
Platform: UNKNOWN
Classifier: Topic :: Scientific/Engineering :: GIS
